nxstaurusgui/NXSMacroGUI.py
nxstaurusgui/__init__.py
nxstaurusgui/config.py
nxstaurusgui/heartbeat.py
nxstaurusgui/serverinfo.py
nxstaurusgui/data/__init__.py
nxstaurusgui/data/config.xml
nxstaurusgui/data/desylogo.png
nxstaurusgui-1.3.0.data/scripts/nxsmacrogui
nxstaurusgui-1.3.0.dist-info/METADATA
nxstaurusgui-1.3.0.dist-info/WHEEL
nxstaurusgui-1.3.0.dist-info/top_level.txt
nxstaurusgui-1.3.0.dist-info/RECORD
